{
  "surah": {
    "number": 74,
    "name": "سُورَةُ المُدَّثِّرِ",
    "englishName": "Al-Muddaththir",
    "englishNameTranslation": "The Cloaked One",
    "turkishName": "Müddessir",
    "numberOfAyahs": 56,
    "revelationType": "Meccan",
    "revelationOrder": 4
  },
  "ayahs": [
    {
      "number": 5496,
      "numberInSurah": 1,
      "transliteration": "Yaaa ayyuhal muddassir",
      "diyanet": "Ey örtüye bürünen!",
      "ozturk": "Ey giysisine bürünüp kenara çekilen!",
      "juz": 29,
      "page": 575,
      "sajda": false,
      "elmali": "Ey bürünen (Müddessir)!",
      "islamoglu": "Sen ey içine kapanan kişi!",
      "bulac": "Ey bürünüp örtünen,",
      "esed": "Sen ey (yalnızlığına) bürünmüş olan!",
      "suleymaniye": "Ey örtüsüne bürünen kişi!",
      "ates": "Ey örtüsüne bürünen,"
    },
    {
      "number": 5497,
      "numberInSurah": 2,
      "transliteration": "Qum fa anzir",
      "diyanet": "Kalk da uyar.",
      "ozturk": "Kalk da uyar!",
      "juz": 29,
      "page": 575,
      "sajda": false,
      "elmali": "Kalk artık inzar et",
      "islamoglu": "Kalk ve (insanları) uyar!",
      "bulac": "Kalk (ve) bundan böyle uyar.",
      "esed": "Kalk ve uyar!",
      "suleymaniye": "Kalk da uyar![1]",
      "ates": "Kalk, uyar."
    },
    {
      "number": 5498,
      "numberInSurah": 3,
      "transliteration": "Wa rabbaka fakabbir",
      "diyanet": "Rabbini yücelt.",
      "ozturk": "Rabbinin yüceliğini duyur!",
      "juz": 29,
      "page": 575,
      "sajda": false,
      "elmali": "Ve rabbını artık büyükle",
      "islamoglu": "Sadece Rabbini yücelt!",
      "bulac": "Rabbini tekbir et (yücelt).",
      "esed": "Rabbinin büyüklüğünü ve yüceliğini an!",
      "suleymaniye": "Sadece Rabbini yücelt![1]",
      "ates": "Rabbini tekbir et (O'nun büyüklüğünü an),"
    },
    {
      "number": 5499,
      "numberInSurah": 4,
      "transliteration": "Wa siyaabaka fatahhir",
      "diyanet": "Giydiklerini temiz tut.",
      "ozturk": "Temizle giysilerini!",
      "juz": 29,
      "page": 575,
      "sajda": false,
      "elmali": "Ve elbiseni artık temizle",
      "islamoglu": "Elbiseni temiz tut!",
      "bulac": "Elbiseni temizle.",
      "esed": "Öz benliğini temiz tut!",
      "suleymaniye": "Elbiselerini tertemiz tut![1]",
      "ates": "Elbiseni temizle,"
    },
    {
      "number": 5500,
      "numberInSurah": 5,
      "transliteration": "Warrujza fahjur",
      "diyanet": "Kötü şeyleri terke devam et.",
      "ozturk": "Uzaklaştır kendinden pisliği!",
      "juz": 29,
      "page": 575,
      "sajda": false,
      "elmali": "Ve o pislikleri artık def' eyle",
      "islamoglu": "Bütün pisliklerden uzak dur!",
      "bulac": "Pislikten kaçınıp uzaklaş.",
      "esed": "Ve bütün pisliklerden kaçın!",
      "suleymaniye": "Bütün pisliklerden uzak dur![1]",
      "ates": "Pislikten kaçın."
    },
    {
      "number": 5501,
      "numberInSurah": 6,
      "transliteration": "Wa laa tamnun tastaksir",
      "diyanet": "Yaptığın iyiliği çok görerek başa kakma.",
      "ozturk": "Çok bularak başa kakma yaptığın iyiliği!",
      "juz": 29,
      "page": 575,
      "sajda": false,
      "elmali": "Hem çoksunarak menn etme",
      "islamoglu": "İyilik yapmayı kazanç kapısı haline getirme! ((Allah için) yaptığın iyiliği çok görme!)",
      "bulac": "Daha çok istekte bulunmak için iyilik yapma.",
      "esed": "İyilik yapmayı kendine kazanç aracı kılma,",
      "suleymaniye": "Yaptığın iyiliği çok görerek başa kakma![1]",
      "ates": "Verdiğini çok bularak başa kakma."
    },
    {
      "number": 5502,
      "numberInSurah": 7,
      "transliteration": "Wa li Rabbika fasbir",
      "diyanet": "Rabbin için sabret.",
      "ozturk": "Ve yalnız Rabbin için dayanıklı kıl benliği!",
      "juz": 29,
      "page": 575,
      "sajda": false,
      "elmali": "Ve rabbın için sabr eyle",
      "islamoglu": "Rabbin hatırına sabret!",
      "bulac": "Rabbin için sabret.",
      "esed": "ama sabırla Rabbine yönel.",
      "suleymaniye": "Rabbin için sabırlı ol /duruşunu bozma![1]",
      "ates": "Rabbin için sabret."
    },
    {
      "number": 5503,
      "numberInSurah": 8,
      "transliteration": "Fa izaa nuqira fin naaqoor",
      "diyanet": "Sura üflendiği vakit, işte o gün, inkarcılara kolay olmayan zorlu bir gündür.",
      "ozturk": "O boruya üfürüldüğünde,",
      "juz": 29,
      "page": 575,
      "sajda": false,
      "elmali": "Çünkü o boru öttürüldü mü bir",
      "islamoglu": "Ve (şu haberi ilet): (Sur) borusuna üflendiği zaman;",
      "bulac": "Çünkü o boruya (sur'a) üfürüldüğü zaman,",
      "esed": "Ve (insanları uyar ki), (yeniden diriliş) suru üflendiği zaman,",
      "suleymaniye": "Kalk borusu çalındığı zaman,[1]",
      "ates": "Sur'a üflendiği zaman"
    },
    {
      "number": 5504,
      "numberInSurah": 9,
      "transliteration": "Fazaalika yawma 'iziny yawmun 'aseer",
      "diyanet": "Sura üflendiği vakit, işte o gün, inkarcılara kolay olmayan zorlu bir gündür.",
      "ozturk": "İşte o gün çok zorlu, çok çetin bir gündür.",
      "juz": 29,
      "page": 575,
      "sajda": false,
      "elmali": "O işte o gün pek zorlu gündür",
      "islamoglu": "evet işte o gün, pek zor bir gün olacaktır,",
      "bulac": "İşte o gün, zorlu bir gündür;",
      "esed": "o Gün, bir ızdırap günü olacaktır,",
      "suleymaniye": "işte o gün zor bir gündür;",
      "ates": "İşte o gün, çetin bir gündür!"
    },
    {
      "number": 5505,
      "numberInSurah": 10,
      "transliteration": "'Alal kaafireena ghayru yaseer",
      "diyanet": "Sura üflendiği vakit, işte o gün, inkarcılara kolay olmayan zorlu bir gündür.",
      "ozturk": "Küfre batmışlar için hiç de kolay değildir.",
      "juz": 29,
      "page": 575,
      "sajda": false,
      "elmali": "Kafirlere hiç kolay değildir",
      "islamoglu": "kafirlerin tümü için hiç de kolay olmayacaktır.",
      "bulac": "Kafirler içinse hiç kolay değildir.",
      "esed": "rahatlama günü değil, (şimdi) hakikati inkar edenler için!",
      "suleymaniye": "hele kafirler için hiç kolay değildir![1]",
      "ates": "Kafirler için kolay değildir."
    },
    {
      "number": 5506,
      "numberInSurah": 11,
      "transliteration": "Zamee wa man khalaqtu waheedaa",
      "diyanet": "Tek olarak yaratıp kendisine bol bol mal, çevresinde bulunan oğullar verdiğim ve nimetleri yaydıkça yaydığım o kimseyi Bana bırak.",
      "ozturk": "Benimle, yarattığım kişiyi baş başa bırak!",
      "juz": 29,
      "page": 575,
      "sajda": false,
      "elmali": "Bırak bana o herifi ki yarattım da temtek",
      "islamoglu": "Beni tek başıma yarattığımla başbaşa bırak!",
      "bulac": "Kendisini tek olarak (ve yapayalnız) yarattığım (şu adam)ı Bana bırak;",
      "esed": "Bana bırak yalnız yarattığım o kişi(yle uğraşma)yı,",
      "suleymaniye": "Beni yarattığım o kişiyle baş başa bırak:[1]",
      "ates": "Benimle şu adamı yalnız bırak ki ben onu tek olarak yarattım."
    },
    {
      "number": 5507,
      "numberInSurah": 12,
      "transliteration": "Wa ja'altu lahoo maalam mamdoodaa",
      "diyanet": "Tek olarak yaratıp kendisine bol bol mal, çevresinde bulunan oğullar verdiğim ve nimetleri yaydıkça yaydığım o kimseyi Bana bırak.",
      "ozturk": "Hesapsız bir mal verdim ona.",
      "juz": 29,
      "page": 575,
      "sajda": false,
      "elmali": "Hem uzun boylu mal verdim",
      "islamoglu": "Ki, geniş maddi imkanlar vermiştim ona!",
      "bulac": "Ki Ben ona, 'alabildiğine geniş kapsamlı bir mal' (servet) verdim.",
      "esed": "kendisine geniş imkanlar verdiğim,",
      "suleymaniye": "Ona bol bol mal mülk verdim,[1]",
      "ates": "Ona uzun boylu mal verdim."
    },
    {
      "number": 5508,
      "numberInSurah": 13,
      "transliteration": "Wa baneena shuhoodaa",
      "diyanet": "Tek olarak yaratıp kendisine bol bol mal, çevresinde bulunan oğullar verdiğim ve nimetleri yaydıkça yaydığım o kimseyi Bana bırak.",
      "ozturk": "Göz doyurucu oğullar verdim.",
      "juz": 29,
      "page": 575,
      "sajda": false,
      "elmali": "Hem göz önünde oğullar",
      "islamoglu": "Bir de (cömertliğimin) şahitleri olan çocuklar...",
      "bulac": "Göz önünde hazır çocuklar (verdim).",
      "esed": "ve (sevginin) şahitleri olarak çocuklar,",
      "suleymaniye": "her zaman yanında olan evlatlar da.[1]",
      "ates": "Göz önünde oğullar (verdim)."
    },
    {
      "number": 5509,
      "numberInSurah": 14,
      "transliteration": "Wa mahhattu lahoo tamheeda",
      "diyanet": "Tek olarak yaratıp kendisine bol bol mal, çevresinde bulunan oğullar verdiğim ve nimetleri yaydıkça yaydığım o kimseyi Bana bırak.",
      "ozturk": "Alabildiğine imkânlar döşedim onun için.",
      "juz": 29,
      "page": 575,
      "sajda": false,
      "elmali": "Hem kendisine bir döşeyip döşedim",
      "islamoglu": "Ve onu bir (bebek gibi) eleyip belemiştim;",
      "bulac": "Ve sayısız imkan ve fırsatları önüne serdim.",
      "esed": "ve hayatına geniş bir ufuk açtığım:",
      "suleymaniye": "Her türlü imkanı önüne serdim[1].",
      "ates": "Kendisine bir döşeyiş döşedim."
    },
    {
      "number": 5510,
      "numberInSurah": 15,
      "transliteration": "Summa yat ma'u an azeed",
      "diyanet": "Bir de verdiğim nimetten artırmamı umar;",
      "ozturk": "Tüm bunlardan sonra hırs ile daha da artırmamı istiyor.",
      "juz": 29,
      "page": 575,
      "sajda": false,
      "elmali": "Sonra da tama' eder ki daha artırayım",
      "islamoglu": "şimdi de kalkmış hırsla daha fazlasını istiyor.",
      "bulac": "Sonra, daha arttırmam için tamah eder (doyumsuz istekte bulunur).",
      "esed": "buna rağmen o, hala ihtirasla verdiğimden daha fazlasını istiyor!",
      "suleymaniye": "Yine de açgözlülükle daha çok vermemi bekliyor![1]",
      "ates": "Hala daha da artırmama göz dikiyor."
    },
    {
      "number": 5511,
      "numberInSurah": 16,
      "transliteration": "Kallaaa innahoo kaana li Aayaatinaa 'aneedaa",
      "diyanet": "Hayır; hayır; çünkü o, Bizim ayetlerimize karşı son derece inatçıdır.",
      "ozturk": "Hayır, iş sanıldığı gibi değil! O, bizim ayetlerimize karşı bir inatçı kesildi.",
      "juz": 29,
      "page": 575,
      "sajda": false,
      "elmali": "Hayır, çünkü o bizim ayetlerimize bir anud kesildi",
      "islamoglu": "Öyle yağma yok! Madem ki o ayetlerimiz inatla (inkara) saplanmıştır.",
      "bulac": "Hayır; çünkü o, Bizim ayetlerimize karşı 'kesin bir inatçıdır.\"",
      "esed": "Evet, o, kendini ayetlerimize karşı bilerek, inatla şartlandırmıştır;",
      "suleymaniye": "Asla (bu beklentisi gerçekleşmeyecek)! Çünkü o, ayetlerimize karşı inatçılık etmektedir[1].",
      "ates": "Hayır, çünkü o bizim ayetlerimize karşı bir inatçı kesildi."
    },
    {
      "number": 5512,
      "numberInSurah": 17,
      "transliteration": "Sa urhiquhoo sa'oodaa",
      "diyanet": "Onu sarp bir yokuşa sardıracağım.",
      "ozturk": "Ben onu dik bir yola süreceğim.",
      "juz": 29,
      "page": 575,
      "sajda": false,
      "elmali": "Ben onu dimdik sarpa sardıracağım",
      "islamoglu": "Ben de onu sarp yokuşa süreceğim.",
      "bulac": "Onu alabildiğine sarp bir yokuşa süreceğim.",
      "esed": "(bu nedenle) onu acı veren çetin bir yokuşa süreceğim!",
      "suleymaniye": "Onu dik bir yokuşa süreceğim[1].",
      "ates": "Onu dimdik bir yokuşa sardıracağım."
    },
    {
      "number": 5513,
      "numberInSurah": 18,
      "transliteration": "Innahoo fakkara wa qaddar",
      "diyanet": "Çünkü o, düşündü, ölçtü biçti;",
      "ozturk": "Derin derin düşündü o; ölçtü-biçti.",
      "juz": 29,
      "page": 576,
      "sajda": false,
      "elmali": "Çünkü o bir düşündü, ölçtü biçti",
      "islamoglu": "Çünkü o (vahiy hakkında) sığ ve yanlış düşündü, ölçüp biçti;",
      "bulac": "Çünkü o, düşündü ve bir ölçü tesbit etti.",
      "esed": "Bakınız, (mesajlarımız hakikati inkara şartlanmış olan birine aktarıldığında, onları nasıl çürüteceğini) düşünür ve (onu) hesaplar,",
      "suleymaniye": "Çünkü o (Kur'an hakkında ne diyeceğini) düşündü taşındı, ölçtü biçti.",
      "ates": "Zira o düşündü, ölçtü, biçti."
    },
    {
      "number": 5514,
      "numberInSurah": 19,
      "transliteration": "Faqutila kayfa qaddar",
      "diyanet": "Canı çıkası, ne biçim ölçüp biçti!",
      "ozturk": "Kahrolası, nasıl bir ölçü kullandı!",
      "juz": 29,
      "page": 576,
      "sajda": false,
      "elmali": "Kahrolası nasıl biçti",
      "islamoglu": "Canı çıkası, nasıl da ölçüp biçti!",
      "bulac": "Kahrolası, nasıl bir ölçü koydu?",
      "esed": "kendini de mahveder böyle hesaplar yaparak:",
      "suleymaniye": "Kahrolasıca, ne biçim ölçtü biçti!",
      "ates": "Kahrolası nasıl da ölçtü, biçti."
    },
    {
      "number": 5515,
      "numberInSurah": 20,
      "transliteration": "Summa qutila kaifa qaddar",
      "diyanet": "Canı çıkası; sonra yine ne biçim ölçüp biçti!",
      "ozturk": "Bir kez daha kahrolası, nasıl bir ölçü kullandı?!",
      "juz": 29,
      "page": 576,
      "sajda": false,
      "elmali": "Sonra kahr olası nasıl biçti",
      "islamoglu": "Bir daha canı çıkası, nasıl da ölçüp biçti!",
      "bulac": "Yine kahrolası, nasıl bir ölçü koydu?",
      "esed": "evet, o kendini mahveder böyle hesaplarla!",
      "suleymaniye": "Ah kahrolasıca, ne biçim ölçtü biçti!",
      "ates": "Yine kahrolası nasıl ölçtü, biçti."
    },
    {
      "number": 5516,
      "numberInSurah": 21,
      "transliteration": "Summa nazar",
      "diyanet": "Sonra baktı;",
      "ozturk": "Sonra baktı.",
      "juz": 29,
      "page": 576,
      "sajda": false,
      "elmali": "Sonra baktı",
      "islamoglu": "Sonra (etrafı) süzdü;",
      "bulac": "Sonra bir baktı.",
      "esed": "Ve sonra (yeni dayanaklar bulmak için çevresine) bakar,",
      "suleymaniye": "Sonra durup baktı.",
      "ates": "Sonra baktı,"
    },
    {
      "number": 5517,
      "numberInSurah": 22,
      "transliteration": "Summa 'abasa wa basar",
      "diyanet": "Sonra kaşlarını çattı, suratını aştı;",
      "ozturk": "Sonra yüzünü buruşturdu, kaşlarını çattı.",
      "juz": 29,
      "page": 576,
      "sajda": false,
      "elmali": "Sonra kaşını çattı ve ekşiyerek surat astı",
      "islamoglu": "ardından surat astı ve rengi attı.",
      "bulac": "Sonra kaşlarını çattı ve yüzünü ekşitti.",
      "esed": "sonra kaşlarını çatarak dik dik süzer,",
      "suleymaniye": "Sonra yüzünü ekşitti ve kaşlarını çattı.",
      "ates": "Sonra surat astı, kaşlarını çattı,"
    },
    {
      "number": 5518,
      "numberInSurah": 23,
      "transliteration": "Summaa adbara wastakbar",
      "diyanet": "Sonra da sırt çevirip büyüklük tasladı.",
      "ozturk": "Sonra arkasını döndü ve böbürlendi.",
      "juz": 29,
      "page": 576,
      "sajda": false,
      "elmali": "Sonra ardına döndü ve büyüklük tasladı da",
      "islamoglu": "En sonunda (hakikate) sırtını döndü ve kibir abidesi kesildi.",
      "bulac": "Sonra da sırt çevirdi ve büyüklük tasladı (istikbar).",
      "esed": "sonunda (mesajlarımıza) sırtını döner ve küstahça böbürlenir,",
      "suleymaniye": "Sonra sırtını döndü ve kibir­lendi[1].",
      "ates": "Sonra arkasını döndü, böbürlendi:"
    },
    {
      "number": 5519,
      "numberInSurah": 24,
      "transliteration": "Faqaala in haazaaa illaa sihruny yu'sar",
      "diyanet": "\"Bu sadece öğretilegelen bir sihirdir. Bu Kuran yalnızca bir insan sözüdür\" dedi.",
      "ozturk": "Şöyle dedi: \"Bu, rivayet edilerek gelen bir büyüden başka şey değil.\"",
      "juz": 29,
      "page": 576,
      "sajda": false,
      "elmali": "Bu, dedi \"başka değil, bir sihri müser",
      "islamoglu": "Nihayet şöyle dedi: \"Bu sadece geçmişten miras kalan bir büyüdür,",
      "bulac": "Böylece: \"Bu, yalnızca 'aktarılarak öğrenilen' bir büyüdür\" dedi.",
      "esed": "ve: \"Bu, (eski zamanlardan) intikal eden büyüleyici bir sözdür!",
      "suleymaniye": "Arkasından şöyle dedi: \"Bu (Kur'an) olsa olsa (öncekilerden) nakledilegelen bir sihirdir![1]",
      "ates": "\"Bu dedi, rivayet edilip öğretilen bir büyüden başka bir şey değildir.\""
    },
    {
      "number": 5520,
      "numberInSurah": 25,
      "transliteration": "In haazaaa illaa qawlul bashar",
      "diyanet": "\"Bu sadece öğretilegelen bir sihirdir. Bu Kuran yalnızca bir insan sözüdür\" dedi.",
      "ozturk": "\"İnsan sözünden başka bir şey değil bu.\"",
      "juz": 29,
      "page": 576,
      "sajda": false,
      "elmali": "Başka değil kavl-i beşer\"",
      "islamoglu": "bu sadece ölümlü bir insan sözüdür.",
      "bulac": "\"Bu, bir beşer sözünden başkası değildir.\"",
      "esed": "Bu, ölümlü beşer sözünden başka bir şey değildir!\" der.",
      "suleymaniye": "Bu, olsa olsa bir insan sö­züdür!\"[1]",
      "ates": "\"Bu, sadece, bir insan sözüdür.\""
    },
    {
      "number": 5521,
      "numberInSurah": 26,
      "transliteration": "Sa usleehi saqar",
      "diyanet": "İşte bu adamı yakıcı bir ateşe yaslayacağım.",
      "ozturk": "Onu sekara fırlatacağım.",
      "juz": 29,
      "page": 576,
      "sajda": false,
      "elmali": "Yaslıyacağım onu Sekare",
      "islamoglu": "Onu Sekar'a yaslayacağım.",
      "bulac": "Onu Ben, cehenneme sürükleyip atacağım.",
      "esed": "(Bu nedenle,) onu (öteki dünyada) cehennem ateşine sokacağım!",
      "suleymaniye": "Onu Sakar'a (cehenneme) sokacağım.[1]",
      "ates": "Onu Sekar'a sokacağım."
    },
    {
      "number": 5522,
      "numberInSurah": 27,
      "transliteration": "Wa maaa adraaka maa saqar",
      "diyanet": "Yakıcı ateşin ne olduğunu sen nerden bilirsin?",
      "ozturk": "Bilir misin nedir sekar?",
      "juz": 29,
      "page": 576,
      "sajda": false,
      "elmali": "Bilir misin hem ne sekar",
      "islamoglu": "Sekar'ın ne olduğunu nasıl bilebilirsin ki sen?",
      "bulac": "Cehennem (sakar) nedir, sen bilir misin?",
      "esed": "Cehennem ateşinin ne olduğunu hiç düşündün mü?",
      "suleymaniye": "Sakar'ın ne olduğunu sana kim bildirebilir!",
      "ates": "Sekar'ın ne olduğunu sen nereden bileceksin?"
    },
    {
      "number": 5523,
      "numberInSurah": 28,
      "transliteration": "Laa tubqee wa laa tazar",
      "diyanet": "O, ne geri bırakır ne de azabdan vazgeçer.",
      "ozturk": "Ortada bir şey bırakmaz, hiçbir şeyi görmezlik etmez o.",
      "juz": 29,
      "page": 576,
      "sajda": false,
      "elmali": "Ne bakıyye kor ne bırakır",
      "islamoglu": "O ne (diri) bırakır, ne de (ölüme) terk eder;",
      "bulac": "Ne alıkoyar, ne bırakır.",
      "esed": "O ne yaşatır, ne de (ölüme) terk eder,",
      "suleymaniye": "O, bırakmaz (ki yaşasın), terk etmez (ki ölsün)[1].",
      "ates": "(Geride bir şey) Komaz, bırakmaz (her şeyi yakıp yok eder)."
    },
    {
      "number": 5524,
      "numberInSurah": 29,
      "transliteration": "Lawwaahatul lilbashar",
      "diyanet": "İnsanın derisini kavurur;",
      "ozturk": "İnsan için tablolar/levhalar/ekranlar sunandır o/deriyi yakıp kavurandır o.",
      "juz": 29,
      "page": 576,
      "sajda": false,
      "elmali": "Beşere susamış bir susuz",
      "islamoglu": "o insana kendi özünü gösterir;",
      "bulac": "Beşere delicesine susamıştır.",
      "esed": "ölümlü insana (nihai hakikati) gösterir.",
      "suleymaniye": "İnsanı kavurup durur![1]",
      "ates": "Durmadan deriler kavurur."
    },
    {
      "number": 5525,
      "numberInSurah": 30,
      "transliteration": "'Alaihaa tis'ata 'ashar",
      "diyanet": "Orada ondokuz bekçi vardır.",
      "ozturk": "Üzerinde ondokuz vardır onun.",
      "juz": 29,
      "page": 576,
      "sajda": false,
      "elmali": "Üzerinde on dokuz",
      "islamoglu": "onun üzerinde on dokuz (melek/e) vardır.",
      "bulac": "Onun üzerinde ondokuz vardır.",
      "esed": "Onun üzerinde ondokuz (güç) vardır.",
      "suleymaniye": "Onun üzerinde on dokuz (melek) vardır[1].",
      "ates": "Üzerinde ondokuz (muhafız) vardır."
    },
    {
      "number": 5526,
      "numberInSurah": 31,
      "transliteration": "Wa maaja''alnaaa As haaban naari illaa malaaa 'ikatanw wa maa ja'alnaa 'iddatahum illaa fitnatal lillazeena kafaroo liyastayqinal lazeena ootul kitaaba wa yazdaadal lazeena aamanooo eemaananw wa laa yartaabal lazeena ootul kitaaba walmu'minoona wa liyaqoolal lazeena fee quloo bihim maradunw walkaafiroona maazaaa araadal laahu bihaazaa masalaa; kazaalika yudillul laahu many yashaaa'u wa yahdee many yashaaa'; wa maa ya'lamu junooda rabbika illaa hoo; wa maa hiya illaa zikraa lil bashar",
      "diyanet": "Cehennemin bekçilerini yalnız meleklerden kılmışızdır. Sayılarını bildirmekle de, ancak inkar edenlerin denenmesini ve kendilerine kitap verilenlerin kesin bilgi edinmesini ve inananların da imanlarının artmasını sağladık. Kendilerine kitap verilenler ve inananlar şüpheye düşmesinler. Kalblerinde hastalık bulunanlar ve inkarcılar: \"Allah bu misalle neyi muradetti?\" desinler. İşte Allah, böylece, dilediğini saptırır, dilediğini de doğru yola eriştirir. Rabbinin ordularını kendisinden başkası bilmez. Bu, insanoğluna bir öğütten ibarettir.",
      "ozturk": "Biz, cehennem yârânını hep melekler yaptık. Ve biz, onların sayılarını da küfre sapanlar için bir imtihandan başka şey yapmadık. Ta ki, kendilerine kitap verilenler iyice ve apaçık bilsinler. İman etmiş olanların imanı artsın. Kendilerine kitap verilmiş olanlarla iman sahipleri kuşkuya düşmesin. Kalplerinde hastalık olanlarla küfre sapmış bulunanlar da; \"Allah bununla neyi örneklendirmek istiyor?\" desinler. İşte böyle. Allah, dilediğini/dileyeni saptırır, dilediğini/dileyeni de doğruya ve güzele kılavuzlar. Rabbinin ordularını ancak O bilir. Bu, insan için bir öğüt verici ve düşündürücüden başka şey değildir.",
      "juz": 29,
      "page": 576,
      "sajda": false,
      "elmali": "Hem biz o ateşin muhafızlarını hep Melaike yaptık, sayılarını da ancak küfr edenler için bir fitne kıldık ki kitab verilmiş olanlar yakin edinsin ve iyman edenlere iyman artırsın, kitab verilenler ve mü'minler şübhelenmesin, kalblerinde bir maraz bulunanlarla kafirler de desin: Allah bununla mesela ne murad etmiş? İşte böyle Allah dilediğini şaşırtır, dilediğini de yola getirir ve rabbının ordularını ancak kendisi bilir ve o ancak bir öğüttür düşünmek için beşer",
      "islamoglu": "Zira yalnızca melaikeyi ateşin muhafızları kıldık; ve onların sayısını inkarda ısrar edenler için bir sınav yaptık; ki böylece önceki vahyin mensupları gönülden ikna olsun ve (ona) iman edenlerin imanları artsın; hem önceki vahyin mensupları hem de (bu vahye) iman edenler bütün kuşkulardan arınsın; ve kalplerinde hastalık olanlar ve inkara gömülenler ise, \"Allah bu temsil ile ne yapmayı diledi?\" diye sorsun! İşte böylece Allah (sapmayı) dileyeni saptırır, (hidayeti) dileyeni ise doğru yola yöneltir. Ve Rabbinin ordularını(n sayısını) Zatından başka kimse bilemez. Nihayet bunlar, ölümlü insan için bir uyarı ve öğütten ibarettir.",
      "bulac": "Biz o ateşin koruyucularını meleklerden başkasını kılmadık. Ve onların sayısını inkar edenler için yalnızca bir fitne (konusu) yaptık ki, kendilerine kitap verilenler, kesin bir bilgiyle inansın, iman edenlerin de imanları artsın; kendilerine kitap verilenler ve iman edenler (böylece) kuşkuya kapılmasın. Kalplerinde bir hastalık olanlar ile kafirler de şöyle desin: \"Allah, bu örnekle neyi anlatmak istedi?\" İşte Allah, dilediğini böyle şaşırtıp saptırır, dilediğini böyle hidayete erdirir. Rabbinin ordularını kendisinden başka (hiç kimse) bilmez. Bu ise, beşer (insan) için yalnızca bir öğüttür.",
      "esed": "Çünkü yalnızca meleki güçleri (cehennem) ateşinin gözcüleri kıldık; ve onların sayısını hakikati inkara şartlanmış olanlar için bir sınama (aracı) yaptık ki böylece daha önce vahye muhatab olanlar (bu ilahi kelamın doğruluğuna) kani olsunlar ve (ona) iman etmiş olanların imanları daha da güçlensin; ve geçmiş vahiylere muhatab olanlar ile (bu vahye) iman edenler bütün şüphelerden kurtulsunlar. Ve kalplerinde hastalık olanlar ile hakikati tamamen reddedenler: \"(Sizin) Allah(ınız) bu temsil ile ne demek istiyor?\" diye sorsunlar. Böylece Allah, (yoldan çıkmak) isteyeni saptırır, (doğruya ulaşmak) isteyeni ise doğru yola ulaştırır. Ve Rabbinin güçlerini Kendisinden başka kimse bilemez. Bütün bunlar ölümlü insan için yalnızca bir uyarıdır.",
      "suleymaniye": "O ateşin (Cehennemin) görevlilerini sadece meleklerden oluşturduk[1]. Sayılarını[2] da kafirler için sırf bir imtihan[3] sebebi yaptık ki kendilerine kitap verilenler (Kur'an'ın Allah'ın kitabı olduğu konusunda) kesin kanaate varsınlar, iman edenlerin güvenleri artsın, kendilerine kitap verilenler ile müminler şüpheye düşmesinler, kalplerinde hastalık olanlarla[4] kafirler de şöyle desinler: \"Allah bu sayıyla neyi amaçlamış olabilir ki![5]\" Böylece Allah, (sapkınlığı) tercih edeni sapkın sayar, (doğru yolu) tercih edeni de yoluna kabul eder. Rabbinin ordularını sadece kendisi bilir[6]. Bunlar, insanlar için sadece doğru bilgidir[7].",
      "ates": "Biz cehennemin muhafızlarını hep melekler yaptık. Onların sayısını da inkar edenler için bir sınav yaptık ki, kendilerine Kitap verilmiş olanlar iyice inansın, inananların da imanı artsın. Kitap verilmiş olanlar ve inananlar kuşkulanmasınlar. Kalblerinde hastalık bulunanlar ve kafirler de: \"Allah bu misalle ne demek istedi?\" desinler. Böylece Allah, dilediğini şaşırtır, dilediğini doğru yola iletir. Rabbinin ordularını ancak kendisi bilir. Bu, insanlara bir uyarıdır."
    },
    {
      "number": 5527,
      "numberInSurah": 32,
      "transliteration": "Kallaa walqamar",
      "diyanet": "Hayır, hayır öğüt almazlar. Aya, dönüp gelen geceye, ağarmakta olan sabaha and olsun ki, içinizden öne geçmek veya geri kalmak isteyen kimseye, insanoğlunu uyarıcı olarak anlatılan cehennem büyük olaylardan biridir.",
      "ozturk": "Hayır, sandıkları gibi değil! Yemin olsun Ay'a,",
      "juz": 29,
      "page": 576,
      "sajda": false,
      "elmali": "Hayır hayır o Kamere",
      "islamoglu": "Evet, ay şahit olsun!",
      "bulac": "Hayır; aya andolsun,",
      "esed": "Evet, hilali düşün!",
      "suleymaniye": "Hayır, hayır; Ay'a yemin olsun[1],",
      "ates": "Hayır, andolsun Aya,"
    },
    {
      "number": 5528,
      "numberInSurah": 33,
      "transliteration": "Wallaili adbar",
      "diyanet": "Hayır, hayır öğüt almazlar. Aya, dönüp gelen geceye, ağarmakta olan sabaha and olsun ki, içinizden öne geçmek veya geri kalmak isteyen kimseye, insanoğlunu uyarıcı olarak anlatılan cehennem büyük olaylardan biridir.",
      "ozturk": "Yemin olsun geceye, sırtını döndüğünde;",
      "juz": 29,
      "page": 576,
      "sajda": false,
      "elmali": "Ve döndüğü dem o geceye",
      "islamoglu": "Geçip giden gece şahit olsun!",
      "bulac": "Dönüp gittiği zaman geceye,",
      "esed": "Geçip gitmekte olan geceyi düşün,",
      "suleymaniye": "dönüp gittiğinde geceye yemin olsun[1]",
      "ates": "Dönüp gitmekte olan geceye,"
    },
    {
      "number": 5529,
      "numberInSurah": 34,
      "transliteration": "Wassub hi izaaa asfar",
      "diyanet": "Hayır, hayır öğüt almazlar. Aya, dönüp gelen geceye, ağarmakta olan sabaha and olsun ki, içinizden öne geçmek veya geri kalmak isteyen kimseye, insanoğlunu uyarıcı olarak anlatılan cehennem büyük olaylardan biridir.",
      "ozturk": "Yemin olsun sabaha, ağarıp ışıdığında,",
      "juz": 29,
      "page": 576,
      "sajda": false,
      "elmali": "Ve açtığı sıra o sabaha kasem olsun ki",
      "islamoglu": "Ve ağaracak olan sabah şahit olsun!",
      "bulac": "Ağardığı zaman sabaha,",
      "esed": "ve ağaran sabahı!",
      "suleymaniye": "ve aydınlandığında sabaha yemin olsun ki[1]",
      "ates": "Ağaran sabaha,"
    },
    {
      "number": 5530,
      "numberInSurah": 35,
      "transliteration": "Innahaa la ihdal kubar",
      "diyanet": "Hayır, hayır öğüt almazlar. Aya, dönüp gelen geceye, ağarmakta olan sabaha and olsun ki, içinizden öne geçmek veya geri kalmak isteyen kimseye, insanoğlunu uyarıcı olarak anlatılan cehennem büyük olaylardan biridir.",
      "ozturk": "Ki o gerçekten en büyüklerden biridir.",
      "juz": 29,
      "page": 576,
      "sajda": false,
      "elmali": "her halde büyüklerin biridir o Sekar",
      "islamoglu": "Şüphesiz o (cehennem ateşi, musibetlerin) en eşsizidir;",
      "bulac": "Gerçekten o, büyük (musibet)lerden biridir.",
      "esed": "Şüphe yok ki bu (cehennem ateşi) gerçekten büyük (bir uyarı)dır",
      "suleymaniye": "O ateş, kesinlikle büyük azaplardan biridir[1];",
      "ates": "Ki o (Sekar), büyük (bela)lardan biridir."
    },
    {
      "number": 5531,
      "numberInSurah": 36,
      "transliteration": "Nazeeral lilbashar",
      "diyanet": "Hayır, hayır öğüt almazlar. Aya, dönüp gelen geceye, ağarmakta olan sabaha and olsun ki, içinizden öne geçmek veya geri kalmak isteyen kimseye, insanoğlunu uyarıcı olarak anlatılan cehennem büyük olaylardan biridir.",
      "ozturk": "İnsan için bir uyarıcıdır.",
      "juz": 29,
      "page": 576,
      "sajda": false,
      "elmali": "Kocundurmak için beşeri",
      "islamoglu": "insan soyu için bir uyarıdır;",
      "bulac": "Beşer (insan) için bir uyarıdır.",
      "esed": "ölümlü insan için bir uyarı",
      "suleymaniye": "insanlar için bir uyarıdır[1].",
      "ates": "İnsanlar için uyarıcıdır;"
    },
    {
      "number": 5532,
      "numberInSurah": 37,
      "transliteration": "Liman shaaa'a minkum any yataqaddama aw yata akhkhar",
      "diyanet": "Hayır, hayır öğüt almazlar. Aya, dönüp gelen geceye, ağarmakta olan sabaha and olsun ki, içinizden öne geçmek veya geri kalmak isteyen kimseye, insanoğlunu uyarıcı olarak anlatılan cehennem büyük olaylardan biridir.",
      "ozturk": "Sizden, öne geçmek yahut arkaya kalmak/erken davranmak yahut gecikmek isteyen için.",
      "juz": 29,
      "page": 576,
      "sajda": false,
      "elmali": "İçinizden ileri gitmek veya geri kalmak istiyen kimseleri",
      "islamoglu": "içinizden öne geçmeyi veya arkada kalmayı dileyen herkes için...",
      "bulac": "Sizlerden öne geçmek veya geride kalmak isteyenler için.",
      "esed": "öne çıkmayı veya geride kalmayı seçen her biriniz için!",
      "suleymaniye": "İçinizden önde gitmeyi veya geri kalmayı tercih edenler[1] için (bir uyarı)[2].",
      "ates": "Sizden (iman yolunda) ileri gitmek veya geri kalmak dileyen kimseler için (uyarıcıdır)."
    },
    {
      "number": 5533,
      "numberInSurah": 38,
      "transliteration": "Kullu nafsim bim kasabat raheenah",
      "diyanet": "Herkes kazancına bağlı bir rehindir;",
      "ozturk": "Her benlik kendi kazandığının bir karşılığıdır.",
      "juz": 29,
      "page": 576,
      "sajda": false,
      "elmali": "Her nefis kazancına bağlıdır",
      "islamoglu": "Her insanın (akıbeti) kendi kazandıklarına bağlıdır;",
      "bulac": "Her nefis, kazandıklarına karşılık bir rehinedir.",
      "esed": "(Hesap Günü) her insan, yapmış olduğu bütün (kötü) fiiller için rehin olarak tutulacaktır;",
      "suleymaniye": "(Hesap günü) Herkes kazandıklarına karşılık rehin tutulur[1].",
      "ates": "Her can, kazandığıyle (Allah katında) rehin alınmıştır."
    },
    {
      "number": 5534,
      "numberInSurah": 39,
      "transliteration": "Illaaa as haabal yameen",
      "diyanet": "Ancak, defteri sağdan verilenler böyle değildir; onlar cennettedirler. Suçlulara: \"Sizi bu yakıcı ateşe sürükleyen nedir?\" diye sorarlar.",
      "ozturk": "Uğur ve bereket yârânı müstesna.",
      "juz": 29,
      "page": 576,
      "sajda": false,
      "elmali": "Ancak ashab-ı yemin",
      "islamoglu": "ancak iyiler müstesna.",
      "bulac": "Ancak Ashab-ı Yemin (sağ ehli) hariç.",
      "esed": "yalnız dürüstlüğü ve erdemli olmayı başaranlar hariç;",
      "suleymaniye": "Defteri sağdan verilenler hariç[1].",
      "ates": "Yalnız sağın adamları (Kitapları sağdan verilenler) hariç."
    },
    {
      "number": 5535,
      "numberInSurah": 40,
      "transliteration": "Fee jannaatiny yata saaa'aloon",
      "diyanet": "Ancak, defteri sağdan verilenler böyle değildir; onlar cennettedirler. Suçlulara: \"Sizi bu yakıcı ateşe sürükleyen nedir?\" diye sorarlar.",
      "ozturk": "Bahçelerdedirler. Birbirlerine soruyorlar,",
      "juz": 29,
      "page": 576,
      "sajda": false,
      "elmali": "Cennetlerdedir, soruşdururlar",
      "islamoglu": "(Onlar) cennetlerde, hep bir ağızdan soracaklar",
      "bulac": "Onlar cennetlerdedirler; birbirlerine sorarlar.",
      "esed": "onlar (cennet) bahçelerinde (oturarak) soracaklar",
      "suleymaniye": "Onlar cennetlerde / bahçelerde olur[1], birbirlerine sorarlar;",
      "ates": "Onlar cennetler içinde soruyorlar;"
    },
    {
      "number": 5536,
      "numberInSurah": 41,
      "transliteration": "'Anil mujrimeen",
      "diyanet": "Ancak, defteri sağdan verilenler böyle değildir; onlar cennettedirler. Suçlulara: \"Sizi bu yakıcı ateşe sürükleyen nedir?\" diye sorarlar.",
      "ozturk": "Suçlular hakkında:",
      "juz": 29,
      "page": 576,
      "sajda": false,
      "elmali": "Mücrimlerden",
      "islamoglu": "günahı hayat tarzı edinenlere:",
      "bulac": "Suçlu günahkarları;",
      "esed": "günahkarlara:",
      "suleymaniye": "suça dalanların halini...[1]",
      "ates": "Suçluların durumunu:"
    },
    {
      "number": 5537,
      "numberInSurah": 42,
      "transliteration": "Maa salakakum fee saqar",
      "diyanet": "Ancak, defteri sağdan verilenler böyle değildir; onlar cennettedirler. Suçlulara: \"Sizi bu yakıcı ateşe sürükleyen nedir?\" diye sorarlar.",
      "ozturk": "\"Sizi sekara sürükleyen nedir?\"",
      "juz": 29,
      "page": 576,
      "sajda": false,
      "elmali": "Nedir, diye: sizi sekare sokan?",
      "islamoglu": "\"Sizi, içinizi yansıtan bu ateşe ne soktu?\"",
      "bulac": "\"Sizi şu cehenneme sürükleyip iten nedir?\"",
      "esed": "\"Sizi bu cehennem ateşine sürükleyen nedir?\"",
      "suleymaniye": "(Sonra onları Sakar'da görür ve şöyle sorarlar:) \"Sizi Sakar'a[1] sürükleyen ne oldu?\"",
      "ates": "\"Sizi şu yakıcı ateşe ne sürükledi?\""
    },
    {
      "number": 5538,
      "numberInSurah": 43,
      "transliteration": "Qaaloo lam naku minal musalleen",
      "diyanet": "Onlar derler ki: \"Namaz kılanlardan değildik.\"",
      "ozturk": "Cevap verdiler: \"Namazı/duayı yerine getirenlerden değildik.\"",
      "juz": 29,
      "page": 576,
      "sajda": false,
      "elmali": "Derler: biz namaz kılanlardan değildik",
      "islamoglu": "Cevap verecekler: \"Biz hem Allah'la bağımızı koparmıştık,",
      "bulac": "Onlar: \"Biz namaz kılanlardan değildik\" dediler.",
      "esed": "Berikiler \"Biz\" diyecekler, \"ne namaz kılanlardan idik,",
      "suleymaniye": "Onlar şöyle derler: \"Biz, kulluk görevlerini yapanlardan[1] değildik.",
      "ates": "(Onlar da) Dediler ki: \"Biz namaz kılanlardan olmadık.\""
    },
    {
      "number": 5539,
      "numberInSurah": 44,
      "transliteration": "Wa lam naku nut'imul miskeen",
      "diyanet": "\"Düşkün kimseyi doyurmuyorduk.\"",
      "ozturk": "\"Yoksulu yedirip doyurmuyorduk.\"",
      "juz": 29,
      "page": 576,
      "sajda": false,
      "elmali": "Ve fukaraya yemek yedirmezdik",
      "islamoglu": "hem de yoksulları doyurmazdık;",
      "bulac": "\"Yoksula yedirmezdik.\"",
      "esed": "ne de yoksulları doyururduk;",
      "suleymaniye": "Çaresiz kalmış birini doyurmazdık[1].",
      "ates": "\"Yoksula da yedirmezdik.\""
    },
    {
      "number": 5540,
      "numberInSurah": 45,
      "transliteration": "Wa kunnaa nakhoodu ma'al khaaa'ideen",
      "diyanet": "\"Batıla dalanlarla biz de dalardık.\"",
      "ozturk": "\"Boş lakırdılara dalanlarla dalar giderdik.\"",
      "juz": 29,
      "page": 576,
      "sajda": false,
      "elmali": "Batakçılarla dalar giderdik",
      "islamoglu": "üstelik (günaha) dalanlarla birlikte biz de dalardık;",
      "bulac": "\"(Batıla ve tutkulara) Dalıp gidenlerle biz de dalar giderdik.\"",
      "esed": "ve kendilerini günaha kaptıran (diğer) günahkarlar ile birlikte günaha dalmıştık;",
      "suleymaniye": "Boş işlere dalanlarla birlikte biz de dalar giderdik[1].",
      "ates": "Boş şeylere dalanlarla birlikte dalardık.\""
    },
    {
      "number": 5541,
      "numberInSurah": 46,
      "transliteration": "Wa kunnaa nukazzibu bi yawmid Deen",
      "diyanet": "\"Ceza gününü yalanlardık.\"",
      "ozturk": "\"Din gününü yalanlıyorduk.\"",
      "juz": 29,
      "page": 576,
      "sajda": false,
      "elmali": "Ve ceza gününe yalan derdik",
      "islamoglu": "hepsinden öte biz Hesap Günü'nü yalanlardık;",
      "bulac": "\"Din (hesap ve ceza) gününü yalan sayıyorduk.\"",
      "esed": "ve Hesap Günü'nü yalanlamıştık,",
      "suleymaniye": "Her şeyin karşılığını bulacağı[1] gün hakkında da hep yalan söylerdik[2].",
      "ates": "\"Ceza gününü yalanlardık.\""
    },
    {
      "number": 5542,
      "numberInSurah": 47,
      "transliteration": "Hattaaa ataanal yaqeen",
      "diyanet": "\"Ölüm bize o haldeyken geldi.\"",
      "ozturk": "\"Nihayet, tartışılmaz ve karşı çıkılmaz bilgi önümüze dikildi.\"",
      "juz": 29,
      "page": 576,
      "sajda": false,
      "elmali": "Ta gelinciye kadar bize o yakin",
      "islamoglu": "ta ki ölüm hakikati bizi gelip buluncaya kadar...\"",
      "bulac": "\"Sonunda yakin (kesin bir gerçek olan ölüm) gelip bize çattı.\"",
      "esed": "(ölüm ile) her şey açık seçik ortaya çıkıncaya kadar.\"",
      "suleymaniye": "Sonunda o kesin gerçek /ölüm bize geldi çattı[1].\"",
      "ates": "\"İşte böyle iken ölüm bize gelip çattı.\""
    },
    {
      "number": 5543,
      "numberInSurah": 48,
      "transliteration": "Famaa tanfa'uhum shafaa'atush shaafi'een",
      "diyanet": "Artık onlara, şefaatçilerin şefaati fayda vermez.",
      "ozturk": "Artık yarar sağlamaz onlara şefaatçilerin şefaati.",
      "juz": 29,
      "page": 577,
      "sajda": false,
      "elmali": "Fakat faide vermez o vakıt şefaati şefaatçilerin",
      "islamoglu": "İşte bunlara hiçbir şefaatçinin şefaati fayda vermeyecek.",
      "bulac": "Artık, şefaat edenlerin şefaati onlara bir yarar sağlamaz.",
      "esed": "Ve böylece, onlar için şefaat edecek olanların hiçbirinin (zerre kadar) faydası olmaz.",
      "suleymaniye": "Artık şefaatçilerin şefaati onlara bir fayda vermeyecek[1].",
      "ates": "Artık onlara şefa'atçilerin şefa'ati fayda vermez."
    },
    {
      "number": 5544,
      "numberInSurah": 49,
      "transliteration": "Famaa lahum 'anittazkirati mu'rideen",
      "diyanet": "Öyleyken, bunlara ne oluyor ki öğütten yüz çeviriyorlar?",
      "ozturk": "Ne oluyor onlara da öğüt verip düşündüren şeyden yüz çeviriyorlar?",
      "juz": 29,
      "page": 577,
      "sajda": false,
      "elmali": "Ya şimdi ne ma'ziretleri var o öğüdden yüz çevirirlerken",
      "islamoglu": "Şu halde o öğüt ve uyarıdan yüz çevirmekle ellerine ne geçecek?",
      "bulac": "Buna rağmen, bunlara ne oluyor ki öğütten yüz çevirip duruyorlar?",
      "esed": "O halde, onlara ne oluyor ki bütün öğütlerden yüz çeviriyorlar,",
      "suleymaniye": "Şimdi bunlara ne oluyor da verilen bu doğru bilgiden (Kur'an'dan[1]) yüz çeviriyorlar[2]?",
      "ates": "Böyle iken onlara ne oluyur ki öğütten yüz çeviriyorlar?"
    },
    {
      "number": 5545,
      "numberInSurah": 50,
      "transliteration": "Ka annahum humurum mustanfirah",
      "diyanet": "Aslandan ürkerek kaçan yabani merkeplere benzerler.",
      "ozturk": "Sağa-sola kaçışan yaban eşekleri gibidirler,",
      "juz": 29,
      "page": 577,
      "sajda": false,
      "elmali": "Sanki ürkmüş yaban eşekleri",
      "islamoglu": "Onlar ürkek yaban eşeklerine benziyorlar;",
      "bulac": "Sanki onlar, ürkmüş yaban eşekleri gibidirler;",
      "esed": "adeta korkuya kapılmış merkepler gibiler,",
      "suleymaniye": "Onlar, ürküp kaçışan eşekler gibidir,",
      "ates": "Yaban eşekleri gibi;"
    },
    {
      "number": 5546,
      "numberInSurah": 51,
      "transliteration": "Farrat min qaswarah",
      "diyanet": "Aslandan ürkerek kaçan yabani merkeplere benzerler.",
      "ozturk": "Arslandan ürkmüşlerdir.",
      "juz": 29,
      "page": 577,
      "sajda": false,
      "elmali": "Arslandan kaçmaktalar",
      "islamoglu": "amansız avcıdan (kaçak eşeklere).",
      "bulac": "Arslandan korkup kaçmışlar.",
      "esed": "aslanlardan ürküp kaçan.",
      "suleymaniye": "aslandan kaçan (eşekler gibi[1]).",
      "ates": "Aslandan ürkmüş."
    },
    {
      "number": 5547,
      "numberInSurah": 52,
      "transliteration": "Bal yureedu kullum ri'im minhum any yu'taa suhufam munashsharah",
      "diyanet": "Hayır; her biri önüne açılıvermiş sahifeler verilmesini ister.",
      "ozturk": "İçlerinden her kişi de istiyor ki, kendisine açılıp saçılmış sayfalar verilsin.",
      "juz": 29,
      "page": 577,
      "sajda": false,
      "elmali": "Yok onlardan her kişi kendisine ayrı sahifelerle tezkireler dağıtılmasını istiyor",
      "islamoglu": "Evet, onların her biri kendilerine açık seçik sayfalar verilmesini ister.",
      "bulac": "Hayır; her biri, kendisine açılmış sahifelerin verilmesini ister.",
      "esed": "Evet, hepsi kendilerine açılmış, açıklanmış vahiyler verilmesi gerektiğini iddia ederler!",
      "suleymaniye": "Aslında onlardan her biri, kendilerine dağıtılacak sayfalar /belgeler getirilmesini ister[1].",
      "ates": "Hayır, onlardan her kişi kendisine açılan sahifeler verilmesini istiyor."
    },
    {
      "number": 5548,
      "numberInSurah": 53,
      "transliteration": "Kallaa bal laa yakhaafoonal aakhirah",
      "diyanet": "Hayır; daha doğrusu ahiretten korkmazlar.",
      "ozturk": "Hayır, öyle şey olmaz! Doğrusu şu ki, âhiretten korkmuyorlar.",
      "juz": 29,
      "page": 577,
      "sajda": false,
      "elmali": "Hayır, doğrusu Ahıretten korkmıyorlar",
      "islamoglu": "Yoo! Aksine onlar ahiret endişesi taşımıyorlar.",
      "bulac": "Hayır; onlar şüphesiz ahiretten korkmuyorlar.",
      "esed": "Asla, onlar öteki dünya(ya inanmazlar ve on)dan korkmazlar.",
      "suleymaniye": "Hayır (bu istedikleri olmayacak)! Aslında onlar ahiretten korkmuyorlar[1].",
      "ates": "Yok yok onlar ahiretten korkmuyorlar."
    },
    {
      "number": 5549,
      "numberInSurah": 54,
      "transliteration": "Kallaaa innahoo tazkirah",
      "diyanet": "Hayır; şüphesiz bu Kuran bir öğüttür.",
      "ozturk": "Hayır, iş, sandıkları gibi değil! O bir öğüt verici/bir düşündürücüdür.",
      "juz": 29,
      "page": 577,
      "sajda": false,
      "elmali": "hayır hayır o muhakkak bir tezkire",
      "islamoglu": "Evet, şüphesiz bu bir öğüttür;",
      "bulac": "Gerçek (şu ki), o (Kur'an,) elbette bir öğüttür.",
      "esed": "Aslında bu bir öğüttür;",
      "suleymaniye": "Hayır (bir belgeye ihtiyaç yok)! Çünkü Kur'an, kesinlikle size verilen doğru bilgidir[1].",
      "ates": "Hayır (iyi bilsinler ki) o (Kur'an) bir ikazdır."
    },
    {
      "number": 5550,
      "numberInSurah": 55,
      "transliteration": "Fa man shaaa'a zakarah",
      "diyanet": "Dileyen kimse öğüt alır.",
      "ozturk": "Dileyen düşünür onu, öğüt alır.",
      "juz": 29,
      "page": 577,
      "sajda": false,
      "elmali": "Dileyen onu tezekkür ede",
      "islamoglu": "Artık dileyen ondan öğüt alır;",
      "bulac": "Artık kim dilerse, öğüt alıp düşünür.",
      "esed": "ve dileyen herkes ondan ders alabilir.",
      "suleymaniye": "Yapması gerekeni yapan o bilgiden yararlanır[1].",
      "ates": "Dileyen onu düşünür, öğüt alır."
    },
    {
      "number": 5551,
      "numberInSurah": 56,
      "transliteration": "Wa maa yazkuroona illaaa any yashaaa'al laah; Huwa ahlut taqwaa wa ahlul maghfirah",
      "diyanet": "Allah dilemeksizin öğüt alamazlar. O, kendisinden korkulmaya daha layıktır ve bağışlamaya daha ehildir.",
      "ozturk": "Ve onlar, Allah'ın dilediği dışında, öğüt alamazlar. Sakındırmaya ve affetmeye ehil olan O'dur.",
      "juz": 29,
      "page": 577,
      "sajda": false,
      "elmali": "Maamafih Allah dilemeyince düşünmezler, koruyacak da odur, mağfiret edecek de",
      "islamoglu": "zaten onlar ancak Allah'ın dilemesi durumunda öğüt alabilirler. O, kendisine karşı sorumluluk duyulmaya ve bağışlamaya en ehil olandır.",
      "bulac": "Allah dilemedikçe onlar öğüt almazlar; takvanın sahibi (onu kabul etmeye ehil olan) O'dur, mağfiretin sahibi (bağışlamaya ehil olan da) O'dur.",
      "esed": "Ama o (öteki dünyaya inanmaya)nlar, Allah dilemedikçe ondan ders almazlar çünkü O, Allah'a karşı sorumluluk bilincinin ve mağfiretin kaynağıdır.",
      "suleymaniye": "Onlar, ancak Allah'ın gerekeni yapması ile[1] bu bilgiden yararlanırlar[2]. Allah, her türlü yanlıştan sakınan ve hep bağışlayandır[3].",
      "ates": "Allah dilemedikçe onlar öğüt almazlar. Takva ve mağfiret ehli O'dur (kendisinden korunmağa, cezasından kaçınmağa layık olan ve günahları bağışlayan yalnız O'dur)."
    }
  ]
}