{
  "surah": "**Ne Zaman**: Tekvir suresi Mekke döneminin başlarında inmiştir.\n\n**Ana Tema**: Kıyamet sahneleri (güneşin dürülmesi, yıldızların dökülmesi), vahyin kaynağı.\n\n**Tarihsel Bağlam**: \"Diri diri toprağa gömülen kıza sorulduğunda\" - kız çocuklarının öldürülmesi eleştirisi.\n\n**Kaynak**: Suyuti; Taberi.",
  "verses": {
    "1-14": "Kıyamet alametleri. Güneşin dürülmesi, yıldızların dökülmesi.",
    "15-21": "Kuran vahyinin güvenilirliği. Cebrail'in tasviri.",
    "8-9": "Diri diri gömülen kız çocuğu. \"Hangi suçtan dolayı öldürüldü?\" Cahiliye'de kız çocuk gömme geleneğine tepki."
  }
}