{"surahNumber":102,"verses":[{"verseNumber":1,"words":[{"position":1,"arabic":"أَلْهَىٰكُمُ","transliteration":"alhākumu","translation":"Diverts you","translationTr":"sizi oyaladı"},{"position":2,"arabic":"ٱلتَّكَاثُرُ","transliteration":"l-takāthuru","translation":"the competition to increase","translationTr":"çokluk yarışı"}]},{"verseNumber":2,"words":[{"position":1,"arabic":"حَتَّىٰ","transliteration":"ḥattā","translation":"Until","translationTr":"nihayet"},{"position":2,"arabic":"زُرْتُمُ","transliteration":"zur'tumu","translation":"you visit","translationTr":"ziyaret ettiniz"},{"position":3,"arabic":"ٱلْمَقَابِرَ","transliteration":"l-maqābira","translation":"the graves","translationTr":"kabirleri"}]},{"verseNumber":3,"words":[{"position":1,"arabic":"كَلَّا","transliteration":"kallā","translation":"Nay","translationTr":"hayır"},{"position":2,"arabic":"سَوْفَ","transliteration":"sawfa","translation":"Soon","translationTr":"yakında"},{"position":3,"arabic":"تَعْلَمُونَ","transliteration":"taʿlamūna","translation":"you will know","translationTr":"bileceksiniz"}]},{"verseNumber":4,"words":[{"position":1,"arabic":"ثُمَّ","transliteration":"thumma","translation":"Then","translationTr":"sonra"},{"position":2,"arabic":"كَلَّا","transliteration":"kallā","translation":"nay","translationTr":"hayır"},{"position":3,"arabic":"سَوْفَ","transliteration":"sawfa","translation":"Soon","translationTr":"yakında"},{"position":4,"arabic":"تَعْلَمُونَ","transliteration":"taʿlamūna","translation":"you will know","translationTr":"bileceksiniz"}]},{"verseNumber":5,"words":[{"position":1,"arabic":"كَلَّا","transliteration":"kallā","translation":"Nay","translationTr":"hayır"},{"position":2,"arabic":"لَوْ","transliteration":"law","translation":"If","translationTr":"keşke"},{"position":3,"arabic":"تَعْلَمُونَ","transliteration":"taʿlamūna","translation":"you know","translationTr":"bilseydiniz"},{"position":4,"arabic":"عِلْمَ","transliteration":"ʿil'ma","translation":"(with) a knowledge","translationTr":"bilgi ile"},{"position":5,"arabic":"ٱلْيَقِينِ","transliteration":"l-yaqīni","translation":"(of) certainty","translationTr":"kesin"}]},{"verseNumber":6,"words":[{"position":1,"arabic":"لَتَرَوُنَّ","transliteration":"latarawunna","translation":"Surely you will see","translationTr":"mutlaka görürdünüz"},{"position":2,"arabic":"ٱلْجَحِيمَ","transliteration":"l-jaḥīma","translation":"the Hellfire","translationTr":"cehennemi"}]},{"verseNumber":7,"words":[{"position":1,"arabic":"ثُمَّ","transliteration":"thumma","translation":"Then","translationTr":"sonra"},{"position":2,"arabic":"لَتَرَوُنَّهَا","transliteration":"latarawunnahā","translation":"surely you will see it","translationTr":"onu göreceksiniz"},{"position":3,"arabic":"عَيْنَ","transliteration":"ʿayna","translation":"(with the) eye","translationTr":"gözle"},{"position":4,"arabic":"ٱلْيَقِينِ","transliteration":"l-yaqīni","translation":"(of) certainty","translationTr":"kesin olarak"}]},{"verseNumber":8,"words":[{"position":1,"arabic":"ثُمَّ","transliteration":"thumma","translation":"Then","translationTr":"sonra"},{"position":2,"arabic":"لَتُسْـَٔلُنَّ","transliteration":"latus'alunna","translation":"surely you will be asked","translationTr":"sorulacaksınız"},{"position":3,"arabic":"يَوْمَئِذٍ","transliteration":"yawma-idhin","translation":"that Day","translationTr":"o gün"},{"position":4,"arabic":"عَنِ","transliteration":"ʿani","translation":"about","translationTr":"ni'metlerden"},{"position":5,"arabic":"ٱلنَّعِيمِ","transliteration":"l-naʿīmi","translation":"the pleasures","translationTr":"the pleasures"}]}]}