{"surahNumber": 105, "verses": [{"verseNumber": 1, "words": [{"position": 1, "arabic": "أَلَمْ", "transliteration": "alam", "translation": "Have not", "translationTr": "görmedin mi?"}, {"position": 2, "arabic": "تَرَ", "transliteration": "tara", "translation": "you seen", "translationTr": "gordun mu"}, {"position": 3, "arabic": "كَيْفَ", "transliteration": "kayfa", "translation": "how", "translationTr": "nasıl"}, {"position": 4, "arabic": "فَعَلَ", "transliteration": "faʿala", "translation": "dealt", "translationTr": "yaptığını"}, {"position": 5, "arabic": "رَبُّكَ", "transliteration": "rabbuka", "translation": "your Lord", "translationTr": "Rabbinin"}, {"position": 6, "arabic": "بِأَصْحَـٰبِ", "transliteration": "bi-aṣḥābi", "translation": "with (the) Companions", "translationTr": "sahiplerine"}, {"position": 7, "arabic": "ٱلْفِيلِ", "transliteration": "l-fīli", "translation": "(of the) Elephant", "translationTr": "fil"}]}, {"verseNumber": 2, "words": [{"position": 1, "arabic": "أَلَمْ", "transliteration": "alam", "translation": "Did not", "translationTr": "çıkarmadı mı?"}, {"position": 2, "arabic": "يَجْعَلْ", "transliteration": "yajʿal", "translation": "He make", "translationTr": "o yapmak"}, {"position": 3, "arabic": "كَيْدَهُمْ", "transliteration": "kaydahum", "translation": "their plan", "translationTr": "onların tuzaklarını"}, {"position": 4, "arabic": "فِى", "transliteration": "fī", "translation": "go", "translationTr": "boşa"}, {"position": 5, "arabic": "تَضْلِيلٍۢ", "transliteration": "taḍlīlin", "translation": "astray", "translationTr": "astray"}]}, {"verseNumber": 3, "words": [{"position": 1, "arabic": "وَأَرْسَلَ", "transliteration": "wa-arsala", "translation": "And He sent", "translationTr": "ve gönderdi"}, {"position": 2, "arabic": "عَلَيْهِمْ", "transliteration": "ʿalayhim", "translation": "against them", "translationTr": "üzerlerine"}, {"position": 3, "arabic": "طَيْرًا", "transliteration": "ṭayran", "translation": "birds", "translationTr": "kuşlar"}, {"position": 4, "arabic": "أَبَابِيلَ", "transliteration": "abābīla", "translation": "(in) flocks", "translationTr": "sürü sürü"}]}, {"verseNumber": 4, "words": [{"position": 1, "arabic": "تَرْمِيهِم", "transliteration": "tarmīhim", "translation": "Striking them", "translationTr": "onlara atıyorlardı"}, {"position": 2, "arabic": "بِحِجَارَةٍۢ", "transliteration": "biḥijāratin", "translation": "with stones", "translationTr": "sertleşmiş taşlar"}, {"position": 3, "arabic": "مِّن", "transliteration": "min", "translation": "of", "translationTr": "çamurdan"}, {"position": 4, "arabic": "سِجِّيلٍۢ", "transliteration": "sijjīlin", "translation": "baked clay", "translationTr": "pisirmis camur"}]}, {"verseNumber": 5, "words": [{"position": 1, "arabic": "فَجَعَلَهُمْ", "transliteration": "fajaʿalahum", "translation": "Then He made them", "translationTr": "nihayet onları yaptı"}, {"position": 2, "arabic": "كَعَصْفٍۢ", "transliteration": "kaʿaṣfin", "translation": "like straw", "translationTr": "ekin yaprağı gibi"}, {"position": 3, "arabic": "مَّأْكُولٍۭ", "transliteration": "makūlin", "translation": "eaten up", "translationTr": "yenmiş"}]}]}