{"surahNumber": 96, "verses": [{"verseNumber": 1, "words": [{"position": 1, "arabic": "ٱقْرَأْ", "transliteration": "iq'ra", "translation": "Read", "translationTr": "oku"}, {"position": 2, "arabic": "بِٱسْمِ", "transliteration": "bi-is'mi", "translation": "in (the) name", "translationTr": "adıyle"}, {"position": 3, "arabic": "رَبِّكَ", "transliteration": "rabbika", "translation": "(of) your Lord", "translationTr": "Rabbinin"}, {"position": 4, "arabic": "ٱلَّذِى", "transliteration": "alladhī", "translation": "the One Who", "translationTr": "yaratan"}, {"position": 5, "arabic": "خَلَقَ", "transliteration": "khalaqa", "translation": "created ", "translationTr": "yaratti"}]}, {"verseNumber": 2, "words": [{"position": 1, "arabic": "خَلَقَ", "transliteration": "khalaqa", "translation": "He created", "translationTr": "O yarattı"}, {"position": 2, "arabic": "ٱلْإِنسَـٰنَ", "transliteration": "l-insāna", "translation": "man", "translationTr": "insanı"}, {"position": 3, "arabic": "مِنْ", "transliteration": "min", "translation": "from", "translationTr": "alaktan"}, {"position": 4, "arabic": "عَلَقٍ", "transliteration": "ʿalaqin", "translation": "a clinging substance", "translationTr": "yapisan bir oz (alak)"}]}, {"verseNumber": 3, "words": [{"position": 1, "arabic": "ٱقْرَأْ", "transliteration": "iq'ra", "translation": "Read", "translationTr": "oku"}, {"position": 2, "arabic": "وَرَبُّكَ", "transliteration": "warabbuka", "translation": "and your Lord", "translationTr": "ve Rabbin"}, {"position": 3, "arabic": "ٱلْأَكْرَمُ", "transliteration": "l-akramu", "translation": "(is) the Most Generous", "translationTr": "en büyük kerem sahibidir"}]}, {"verseNumber": 4, "words": [{"position": 1, "arabic": "ٱلَّذِى", "transliteration": "alladhī", "translation": "The One Who", "translationTr": "O ki"}, {"position": 2, "arabic": "عَلَّمَ", "transliteration": "ʿallama", "translation": "taught", "translationTr": "öğretti"}, {"position": 3, "arabic": "بِٱلْقَلَمِ", "transliteration": "bil-qalami", "translation": "by the pen", "translationTr": "kalemle"}]}, {"verseNumber": 5, "words": [{"position": 1, "arabic": "عَلَّمَ", "transliteration": "ʿallama", "translation": "Taught", "translationTr": "öğretti"}, {"position": 2, "arabic": "ٱلْإِنسَـٰنَ", "transliteration": "l-insāna", "translation": "man", "translationTr": "insana"}, {"position": 3, "arabic": "مَا", "transliteration": "mā", "translation": "what", "translationTr": "şeyi"}, {"position": 4, "arabic": "لَمْ", "transliteration": "lam", "translation": "not", "translationTr": "bilmediği"}, {"position": 5, "arabic": "يَعْلَمْ", "transliteration": "yaʿlam", "translation": "he knew", "translationTr": "o bildi"}]}, {"verseNumber": 6, "words": [{"position": 1, "arabic": "كَلَّآ", "transliteration": "kallā", "translation": "Nay", "translationTr": "hayır"}, {"position": 2, "arabic": "إِنَّ", "transliteration": "inna", "translation": "Indeed", "translationTr": "şüphesiz"}, {"position": 3, "arabic": "ٱلْإِنسَـٰنَ", "transliteration": "l-insāna", "translation": "man", "translationTr": "insan"}, {"position": 4, "arabic": "لَيَطْغَىٰٓ", "transliteration": "layaṭghā", "translation": "surely transgresses", "translationTr": "azar"}]}, {"verseNumber": 7, "words": [{"position": 1, "arabic": "أَن", "transliteration": "an", "translation": "That", "translationTr": "için"}, {"position": 2, "arabic": "رَّءَاهُ", "transliteration": "raāhu", "translation": "he sees himself", "translationTr": "kendini gördüğü"}, {"position": 3, "arabic": "ٱسْتَغْنَىٰٓ", "transliteration": "is'taghnā", "translation": "self-sufficient", "translationTr": "zengin (kendine yeterli)"}]}, {"verseNumber": 8, "words": [{"position": 1, "arabic": "إِنَّ", "transliteration": "inna", "translation": "Indeed", "translationTr": "şüphesiz"}, {"position": 2, "arabic": "إِلَىٰ", "transliteration": "ilā", "translation": "to", "translationTr": "Rabbinedir"}, {"position": 3, "arabic": "رَبِّكَ", "transliteration": "rabbika", "translation": "your Lord", "translationTr": "Rabbin"}, {"position": 4, "arabic": "ٱلرُّجْعَىٰٓ", "transliteration": "l-ruj'ʿā", "translation": "(is) the return", "translationTr": "dönüş"}]}, {"verseNumber": 9, "words": [{"position": 1, "arabic": "أَرَءَيْتَ", "transliteration": "ara-ayta", "translation": "Have you seen", "translationTr": "gördün mü?"}, {"position": 2, "arabic": "ٱلَّذِى", "transliteration": "alladhī", "translation": "the one who", "translationTr": "şu"}, {"position": 3, "arabic": "يَنْهَىٰ", "transliteration": "yanhā", "translation": "forbids", "translationTr": "men'edeni"}]}, {"verseNumber": 10, "words": [{"position": 1, "arabic": "عَبْدًا", "transliteration": "ʿabdan", "translation": "A slave", "translationTr": "bir kulu?"}, {"position": 2, "arabic": "إِذَا", "transliteration": "idhā", "translation": "when", "translationTr": "zaman"}, {"position": 3, "arabic": "صَلَّىٰٓ", "transliteration": "ṣallā", "translation": "he prays", "translationTr": "namaz kıldığı"}]}, {"verseNumber": 11, "words": [{"position": 1, "arabic": "أَرَءَيْتَ", "transliteration": "ara-ayta", "translation": "Have you seen", "translationTr": "gördün mü?"}, {"position": 2, "arabic": "إِن", "transliteration": "in", "translation": "if", "translationTr": "ya"}, {"position": 3, "arabic": "كَانَ", "transliteration": "kāna", "translation": "he is", "translationTr": "olursa"}, {"position": 4, "arabic": "عَلَى", "transliteration": "ʿalā", "translation": "upon", "translationTr": "üzerinde"}, {"position": 5, "arabic": "ٱلْهُدَىٰٓ", "transliteration": "l-hudā", "translation": "[the] guidance", "translationTr": "doğru yol"}]}, {"verseNumber": 12, "words": [{"position": 1, "arabic": "أَوْ", "transliteration": "aw", "translation": "Or", "translationTr": "yahut"}, {"position": 2, "arabic": "أَمَرَ", "transliteration": "amara", "translation": "he enjoins", "translationTr": "emrederse"}, {"position": 3, "arabic": "بِٱلتَّقْوَىٰٓ", "transliteration": "bil-taqwā", "translation": "[of the] righteousness", "translationTr": "korunmayı"}]}, {"verseNumber": 13, "words": [{"position": 1, "arabic": "أَرَءَيْتَ", "transliteration": "ara-ayta", "translation": "Have you seen", "translationTr": "gördün mü?"}, {"position": 2, "arabic": "إِن", "transliteration": "in", "translation": "if", "translationTr": "ya"}, {"position": 3, "arabic": "كَذَّبَ", "transliteration": "kadhaba", "translation": "he denies", "translationTr": "yalanlarsa?"}, {"position": 4, "arabic": "وَتَوَلَّىٰٓ", "transliteration": "watawallā", "translation": "and turns away", "translationTr": "ve yüz çevirirse?"}]}, {"verseNumber": 14, "words": [{"position": 1, "arabic": "أَلَمْ", "transliteration": "alam", "translation": "Does not", "translationTr": "bilmedi mi (o)?"}, {"position": 2, "arabic": "يَعْلَم", "transliteration": "yaʿlam", "translation": "he know", "translationTr": "bilsin"}, {"position": 3, "arabic": "بِأَنَّ", "transliteration": "bi-anna", "translation": "that", "translationTr": "muhakkak"}, {"position": 4, "arabic": "ٱللَّهَ", "transliteration": "l-laha", "translation": "Allah", "translationTr": "Allah'ın"}, {"position": 5, "arabic": "يَرَىٰ", "transliteration": "yarā", "translation": "sees", "translationTr": "gördüğünü"}]}, {"verseNumber": 15, "words": [{"position": 1, "arabic": "كَلَّا", "transliteration": "kallā", "translation": "Nay", "translationTr": "hayır"}, {"position": 2, "arabic": "لَئِن", "transliteration": "la-in", "translation": "If", "translationTr": "eğer"}, {"position": 3, "arabic": "لَّمْ", "transliteration": "lam", "translation": "not", "translationTr": "bundan vazgeçmezse"}, {"position": 4, "arabic": "يَنتَهِ", "transliteration": "yantahi", "translation": "he desists", "translationTr": "o desists"}, {"position": 5, "arabic": "لَنَسْفَعًۢا", "transliteration": "lanasfaʿan", "translation": "surely We will drag him", "translationTr": "mutlaka yakalarız"}, {"position": 6, "arabic": "بِٱلنَّاصِيَةِ", "transliteration": "bil-nāṣiyati", "translation": "by the forelock", "translationTr": "perçeminden"}]}, {"verseNumber": 16, "words": [{"position": 1, "arabic": "نَاصِيَةٍۢ", "transliteration": "nāṣiyatin", "translation": "A forelock", "translationTr": "perçem(den)"}, {"position": 2, "arabic": "كَـٰذِبَةٍ", "transliteration": "kādhibatin", "translation": "lying", "translationTr": "yalancı"}, {"position": 3, "arabic": "خَاطِئَةٍۢ", "transliteration": "khāṭi-atin", "translation": "sinful", "translationTr": "günahkar"}]}, {"verseNumber": 17, "words": [{"position": 1, "arabic": "فَلْيَدْعُ", "transliteration": "falyadʿu", "translation": "Then let him call", "translationTr": "o zaman çağırsın"}, {"position": 2, "arabic": "نَادِيَهُۥ", "transliteration": "nādiyahu", "translation": "his associates", "translationTr": "meclisini"}]}, {"verseNumber": 18, "words": [{"position": 1, "arabic": "سَنَدْعُ", "transliteration": "sanadʿu", "translation": "We will call", "translationTr": "biz de çağıracağız"}, {"position": 2, "arabic": "ٱلزَّبَانِيَةَ", "transliteration": "l-zabāniyata", "translation": "the Angels of Hell", "translationTr": "zebanileri"}]}, {"verseNumber": 19, "words": [{"position": 1, "arabic": "كَلَّا", "transliteration": "kallā", "translation": "Nay", "translationTr": "hayır"}, {"position": 2, "arabic": "لَا", "transliteration": "lā", "translation": "(Do) not", "translationTr": "ona boyun eğme"}, {"position": 3, "arabic": "تُطِعْهُ", "transliteration": "tuṭiʿ'hu", "translation": "obey him", "translationTr": "itaat etmek him"}, {"position": 4, "arabic": "وَٱسْجُدْ", "transliteration": "wa-us'jud", "translation": "But prostrate", "translationTr": "secde et"}, {"position": 5, "arabic": "وَٱقْتَرِب ۩", "transliteration": "wa-iq'tarib", "translation": "and draw near (to Allah)", "translationTr": "ve yaklaş"}]}]}